difai/__init__.py
difai/main.py
difai/py.typed
difai-0.9.73.dist-info/entry_points.txt
difai-0.9.73.dist-info/WHEEL
difai-0.9.73.dist-info/METADATA
difai-0.9.73.dist-info/RECORD
