Metadata-Version: 2.1
Name: difai
Version: 0.9.73
Summary: 'Did I forget any imports' generates requirement files for you
Home-page: https://gitlab.com/marvin.vanaalst/difai
License: WTFPL
Keywords: packaging
Author: Marvin van Aalst
Author-email: marvin.vanaalst@gmail.com
Maintainer: Marvin van Aalst
Maintainer-email: marvin.vanaalst@gmail.com
Requires-Python: >=3.8,<4.0
Classifier: License :: Other/Proprietary License
Classifier: Programming Language :: Python :: 3
Classifier: Programming Language :: Python :: 3.8
Classifier: Programming Language :: Python :: 3.9
Classifier: Programming Language :: Python :: 3.10
Classifier: Programming Language :: Python :: 3.11
Classifier: Topic :: Software Development :: Libraries :: Python Modules
Requires-Dist: nbconvert (>=7.0.0,<8.0.0)
Requires-Dist: nbformat (>=5.6.0,<6.0.0)
Requires-Dist: pip-tools (>=6.8.0,<7.0.0)
Requires-Dist: typer (>=0.6.1,<0.7.0)
Project-URL: Documentation, https://gitlab.com/marvin.vanaalst/difai
Project-URL: Repository, https://gitlab.com/marvin.vanaalst/difai
